pyhtml_desktop/__init__.py
pyhtml_desktop-1.1.3.dist-info/METADATA
pyhtml_desktop-1.1.3.dist-info/WHEEL
pyhtml_desktop-1.1.3.dist-info/top_level.txt
pyhtml_desktop-1.1.3.dist-info/RECORD
