Metadata-Version: 2.1
Name: pyhtml-desktop
Version: 1.1.3
Summary: build desktop apps with Python and HTML
Home-page: UNKNOWN
Author: Kellan Butler
Author-email: kellanbutler52@gmail.com
License: UNKNOWN
Project-URL: Github, https://github.com/kellantech/pyhtmldesktop/
Keywords: python,html
Platform: UNKNOWN
Classifier: Development Status :: 4 - Beta
Classifier: Intended Audience :: Developers
Classifier: Programming Language :: Python :: 3
Classifier: Operating System :: POSIX :: Linux
Requires-Dist: beautifulsoup4
